{"CreationDate":"\/Date(-62135596800000)\/","AverageQuestionsPerDay":0,"AverageAnswersPerDay":0,"AveragePostsPerDay":0,"Views":0,"UpVotes":0,"DownVotes":0,"AccountId":21885,"LastAccessDate":"\/Date(-62135596800000)\/","Reputation":0,"PostStats":{"PostsMade":0,"TotalViews":0,"Questions":18,"TotalWordsForQuestions":2377,"TotalWordsForAnswers":1002,"TotalTitleWordCount":200,"HighestScoredQuestion":17,"LowestScoredQuestion":-3,"TotalCommentsOnQuestions":0,"Answers":5,"HighestScoredAnswer":1,"LowestScoredAnswer":-3,"TotalCommentsOnPosts":0,"TotalCommentsOnAnswers":0,"TotalAcceptedAnswers":0,"AverageWordsPerAnswer":200.4,"AverageViewsPerPost":0,"AverageAcceptedAnswers":0,"LongestQuestionWordCount":388,"ShortestQuestionWordCount":28,"LongestAnswerWordCount":312,"ShortestAnswerWordCount":70,"LongestQuestionTitleWordCount":21,"AverageQuestionTitleWordCount":0,"AverageWordsPerQuestion":132.055555555556,"QuestionIds":[28623,28633,28993,41460,42361,46651,46853,47564,47656,48418,48444,48585,48678,48696,48770,51799,52073,54277],"AnswerIds":[46649,47967,48650,48671,48736],"Id":null},"BadgeStats":{"TotalBadges":0,"TotalTagBadges":0,"Badges":[{"Id":0,"Class":3,"TagBased":false,"DateEarned":"\/Date(1410959716663)\/","Name":"Editor"},{"Id":0,"Class":3,"TagBased":false,"DateEarned":"\/Date(1410968987490)\/","Name":"Student"},{"Id":0,"Class":3,"TagBased":false,"DateEarned":"\/Date(1410974925407)\/","Name":"Supporter"},{"Id":0,"Class":3,"TagBased":false,"DateEarned":"\/Date(1410985579337)\/","Name":"Peer Pressure"},{"Id":0,"Class":3,"TagBased":false,"DateEarned":"\/Date(1411152009677)\/","Name":"Scholar"},{"Id":0,"Class":3,"TagBased":false,"DateEarned":"\/Date(1411590253137)\/","Name":"Autobiographer"},{"Id":0,"Class":3,"TagBased":false,"DateEarned":"\/Date(1413009488610)\/","Name":"Commentator"},{"Id":0,"Class":3,"TagBased":false,"DateEarned":"\/Date(1433505684843)\/","Name":"Custodian"},{"Id":0,"Class":3,"TagBased":false,"DateEarned":"\/Date(1436535643947)\/","Name":"Popular Question"},{"Id":0,"Class":3,"TagBased":false,"DateEarned":"\/Date(1436542588433)\/","Name":"Nice Question"},{"Id":0,"Class":2,"TagBased":false,"DateEarned":"\/Date(1436601905627)\/","Name":"Notable Question"},{"Id":0,"Class":3,"TagBased":false,"DateEarned":"\/Date(1436617124310)\/","Name":"Critic"},{"Id":0,"Class":3,"TagBased":false,"DateEarned":"\/Date(1436659675677)\/","Name":"Teacher"},{"Id":0,"Class":3,"TagBased":false,"DateEarned":"\/Date(1442173314947)\/","Name":"Nice Question"},{"Id":0,"Class":2,"TagBased":false,"DateEarned":"\/Date(1442322870530)\/","Name":"Yearling"},{"Id":0,"Class":3,"TagBased":false,"DateEarned":"\/Date(1443202744157)\/","Name":"Nice Question"}],"Id":null,"MostEarnedBadge":null},"CommentStats":{"Comments":81,"LongestCommentWordCount":106,"ShortestCommentWordCount":3,"AverageCommentWordCount":36.4691358024691,"AverageCommentScore":0.135802469135802,"TotalCommentWordCount":2954,"HighestScoredComment":5,"LowestScoredComment":0,"CommentScores":[0,0,0,0,0,0,0,0,1,0,0,0,0,0,0,0,0,1,0,0,0,0,0,0,1,5,0,0,0,0,0,0,0,0,0,0,0,1,0,1,0,0,0,0,0,0,0,0,0,0,0,0,0,0,1,0,0,0,0,0,0,0,0,0,0,0,0,0,0,0,0,0,0,0,0,0,0,0,0,0,0],"Id":null},"Name":null,"Id":"academia.stackexchange.com-21885","AboutMe":null,"Location":null}
