{"CreationDate":"\/Date(-62135596800000)\/","AverageQuestionsPerDay":0,"AverageAnswersPerDay":0,"AveragePostsPerDay":0,"Views":0,"UpVotes":0,"DownVotes":0,"AccountId":60,"LastAccessDate":"\/Date(-62135596800000)\/","Reputation":0,"PostStats":{"PostsMade":0,"TotalViews":0,"Questions":0,"TotalWordsForQuestions":0,"TotalWordsForAnswers":2298,"TotalTitleWordCount":0,"HighestScoredQuestion":0,"LowestScoredQuestion":0,"TotalCommentsOnQuestions":0,"Answers":25,"HighestScoredAnswer":45,"LowestScoredAnswer":0,"TotalCommentsOnPosts":0,"TotalCommentsOnAnswers":0,"TotalAcceptedAnswers":0,"AverageWordsPerAnswer":91.92,"AverageViewsPerPost":0,"AverageAcceptedAnswers":0,"LongestQuestionWordCount":0,"ShortestQuestionWordCount":0,"LongestAnswerWordCount":268,"ShortestAnswerWordCount":22,"LongestQuestionTitleWordCount":0,"AverageQuestionTitleWordCount":0,"AverageWordsPerQuestion":0,"QuestionIds":[],"AnswerIds":[250,284,626,45758,45760,46214,46216,46221,46339,46398,46399,46871,46872,46944,47035,47042,47051,47121,47153,47797,56606,61004,61381,61640,61874],"Id":null},"BadgeStats":{"TotalBadges":0,"TotalTagBadges":0,"Badges":[{"Id":0,"Class":3,"TagBased":false,"DateEarned":"\/Date(1329262471640)\/","Name":"Precognitive"},{"Id":0,"Class":3,"TagBased":false,"DateEarned":"\/Date(1329418695867)\/","Name":"Supporter"},{"Id":0,"Class":3,"TagBased":false,"DateEarned":"\/Date(1329640034720)\/","Name":"Teacher"},{"Id":0,"Class":2,"TagBased":false,"DateEarned":"\/Date(1329854588540)\/","Name":"Beta"},{"Id":0,"Class":3,"TagBased":false,"DateEarned":"\/Date(1432754268223)\/","Name":"Autobiographer"},{"Id":0,"Class":2,"TagBased":false,"DateEarned":"\/Date(1432845608867)\/","Name":"Yearling"},{"Id":0,"Class":3,"TagBased":false,"DateEarned":"\/Date(1432873339817)\/","Name":"Critic"},{"Id":0,"Class":3,"TagBased":false,"DateEarned":"\/Date(1433107727010)\/","Name":"Citizen Patrol"},{"Id":0,"Class":3,"TagBased":false,"DateEarned":"\/Date(1433107989940)\/","Name":"Commentator"},{"Id":0,"Class":3,"TagBased":false,"DateEarned":"\/Date(1433119176997)\/","Name":"Revival"},{"Id":0,"Class":3,"TagBased":false,"DateEarned":"\/Date(1433820086543)\/","Name":"Editor"},{"Id":0,"Class":3,"TagBased":false,"DateEarned":"\/Date(1433893471040)\/","Name":"Suffrage"},{"Id":0,"Class":2,"TagBased":false,"DateEarned":"\/Date(1433974054530)\/","Name":"Civic Duty"},{"Id":0,"Class":2,"TagBased":false,"DateEarned":"\/Date(1434136137423)\/","Name":"Yearling"},{"Id":0,"Class":3,"TagBased":false,"DateEarned":"\/Date(1435004638920)\/","Name":"Custodian"},{"Id":0,"Class":2,"TagBased":false,"DateEarned":"\/Date(1435021370150)\/","Name":"Enthusiast"},{"Id":0,"Class":3,"TagBased":false,"DateEarned":"\/Date(1435177949387)\/","Name":"Informed"},{"Id":0,"Class":3,"TagBased":false,"DateEarned":"\/Date(1436816571460)\/","Name":"Nice Answer"},{"Id":0,"Class":2,"TagBased":false,"DateEarned":"\/Date(1445458767860)\/","Name":"Yearling"},{"Id":0,"Class":3,"TagBased":false,"DateEarned":"\/Date(1451912130363)\/","Name":"Nice Answer"},{"Id":0,"Class":2,"TagBased":false,"DateEarned":"\/Date(1452114573023)\/","Name":"Good Answer"},{"Id":0,"Class":2,"TagBased":false,"DateEarned":"\/Date(1455488186310)\/","Name":"Yearling"}],"Id":null,"MostEarnedBadge":null},"CommentStats":{"Comments":28,"LongestCommentWordCount":103,"ShortestCommentWordCount":8,"AverageCommentWordCount":40.7857142857143,"AverageCommentScore":0.428571428571429,"TotalCommentWordCount":1142,"HighestScoredComment":4,"LowestScoredComment":0,"CommentScores":[0,0,0,0,4,0,0,3,0,0,0,1,0,0,0,0,0,0,0,0,0,3,0,0,1,0,0,0],"Id":null},"Name":null,"Id":"academia.stackexchange.com-60","AboutMe":null,"Location":null}
