{"CreationDate":"\/Date(-62135596800000)\/","AverageQuestionsPerDay":0,"AverageAnswersPerDay":0,"AveragePostsPerDay":0,"Views":0,"UpVotes":0,"DownVotes":0,"AccountId":7262,"LastAccessDate":"\/Date(-62135596800000)\/","Reputation":0,"PostStats":{"PostsMade":0,"TotalViews":0,"Questions":0,"TotalWordsForQuestions":0,"TotalWordsForAnswers":377,"TotalTitleWordCount":0,"HighestScoredQuestion":0,"LowestScoredQuestion":0,"TotalCommentsOnQuestions":0,"Answers":2,"HighestScoredAnswer":1,"LowestScoredAnswer":-2,"TotalCommentsOnPosts":0,"TotalCommentsOnAnswers":0,"TotalAcceptedAnswers":0,"AverageWordsPerAnswer":188.5,"AverageViewsPerPost":0,"AverageAcceptedAnswers":0,"LongestQuestionWordCount":0,"ShortestQuestionWordCount":0,"LongestAnswerWordCount":287,"ShortestAnswerWordCount":90,"LongestQuestionTitleWordCount":0,"AverageQuestionTitleWordCount":0,"AverageWordsPerQuestion":0,"QuestionIds":[],"AnswerIds":[10293,10295],"Id":null},"BadgeStats":{"TotalBadges":0,"TotalTagBadges":0,"Badges":[{"Id":0,"Class":3,"TagBased":false,"DateEarned":"\/Date(1369813392143)\/","Name":"Teacher"},{"Id":0,"Class":3,"TagBased":false,"DateEarned":"\/Date(1411590807377)\/","Name":"Autobiographer"}],"Id":null,"MostEarnedBadge":null},"CommentStats":{"Comments":2,"LongestCommentWordCount":48,"ShortestCommentWordCount":40,"AverageCommentWordCount":44,"AverageCommentScore":0.5,"TotalCommentWordCount":88,"HighestScoredComment":1,"LowestScoredComment":0,"CommentScores":[0,1],"Id":null},"Name":null,"Id":"academia.stackexchange.com-7262","AboutMe":null,"Location":null}
