{"CreationDate":"\/Date(-62135596800000)\/","AverageQuestionsPerDay":0,"AverageAnswersPerDay":0,"AveragePostsPerDay":0,"Views":0,"UpVotes":0,"DownVotes":0,"AccountId":7328,"LastAccessDate":"\/Date(-62135596800000)\/","Reputation":0,"PostStats":{"PostsMade":0,"TotalViews":0,"Questions":14,"TotalWordsForQuestions":2217,"TotalWordsForAnswers":1085,"TotalTitleWordCount":137,"HighestScoredQuestion":53,"LowestScoredQuestion":0,"TotalCommentsOnQuestions":0,"Answers":5,"HighestScoredAnswer":9,"LowestScoredAnswer":0,"TotalCommentsOnPosts":0,"TotalCommentsOnAnswers":0,"TotalAcceptedAnswers":0,"AverageWordsPerAnswer":217,"AverageViewsPerPost":0,"AverageAcceptedAnswers":0,"LongestQuestionWordCount":288,"ShortestQuestionWordCount":75,"LongestAnswerWordCount":296,"ShortestAnswerWordCount":138,"LongestQuestionTitleWordCount":14,"AverageQuestionTitleWordCount":0,"AverageWordsPerQuestion":158.357142857143,"QuestionIds":[10411,11555,29294,29863,34631,40955,42511,44466,46324,55472,57007,60377,62282,63080],"AnswerIds":[24197,44234,47743,56434,58781],"Id":null},"BadgeStats":{"TotalBadges":0,"TotalTagBadges":0,"Badges":[{"Id":0,"Class":3,"TagBased":false,"DateEarned":"\/Date(1370206991197)\/","Name":"Supporter"},{"Id":0,"Class":3,"TagBased":false,"DateEarned":"\/Date(1370213607353)\/","Name":"Student"},{"Id":0,"Class":3,"TagBased":false,"DateEarned":"\/Date(1370279420320)\/","Name":"Nice Question"},{"Id":0,"Class":3,"TagBased":false,"DateEarned":"\/Date(1370942611407)\/","Name":"Scholar"},{"Id":0,"Class":2,"TagBased":false,"DateEarned":"\/Date(1401742761797)\/","Name":"Yearling"},{"Id":0,"Class":3,"TagBased":false,"DateEarned":"\/Date(1404148190860)\/","Name":"Teacher"},{"Id":0,"Class":3,"TagBased":false,"DateEarned":"\/Date(1410453663207)\/","Name":"Critic"},{"Id":0,"Class":3,"TagBased":false,"DateEarned":"\/Date(1412017168247)\/","Name":"Suffrage"},{"Id":0,"Class":3,"TagBased":false,"DateEarned":"\/Date(1412216107920)\/","Name":"Editor"},{"Id":0,"Class":3,"TagBased":false,"DateEarned":"\/Date(1413205684773)\/","Name":"Nice Question"},{"Id":0,"Class":3,"TagBased":false,"DateEarned":"\/Date(1413211555860)\/","Name":"Popular Question"},{"Id":0,"Class":2,"TagBased":false,"DateEarned":"\/Date(1413408861300)\/","Name":"Civic Duty"},{"Id":0,"Class":3,"TagBased":false,"DateEarned":"\/Date(1419198276150)\/","Name":"Nice Question"},{"Id":0,"Class":3,"TagBased":false,"DateEarned":"\/Date(1419209602073)\/","Name":"Curious"},{"Id":0,"Class":3,"TagBased":false,"DateEarned":"\/Date(1424329731553)\/","Name":"Popular Question"},{"Id":0,"Class":3,"TagBased":false,"DateEarned":"\/Date(1425482539630)\/","Name":"Popular Question"},{"Id":0,"Class":3,"TagBased":false,"DateEarned":"\/Date(1425486303217)\/","Name":"Nice Question"},{"Id":0,"Class":3,"TagBased":false,"DateEarned":"\/Date(1430314209057)\/","Name":"Custodian"},{"Id":0,"Class":3,"TagBased":false,"DateEarned":"\/Date(1433019423587)\/","Name":"Nice Question"},{"Id":0,"Class":3,"TagBased":false,"DateEarned":"\/Date(1433107989940)\/","Name":"Popular Question"},{"Id":0,"Class":2,"TagBased":false,"DateEarned":"\/Date(1433162002843)\/","Name":"Good Question"},{"Id":0,"Class":2,"TagBased":false,"DateEarned":"\/Date(1433278981937)\/","Name":"Yearling"},{"Id":0,"Class":3,"TagBased":false,"DateEarned":"\/Date(1444172042417)\/","Name":"Commentator"},{"Id":0,"Class":3,"TagBased":false,"DateEarned":"\/Date(1445974402133)\/","Name":"Popular Question"},{"Id":0,"Class":3,"TagBased":false,"DateEarned":"\/Date(1445974701553)\/","Name":"Nice Question"},{"Id":0,"Class":3,"TagBased":false,"DateEarned":"\/Date(1445986644537)\/","Name":"Popular Question"},{"Id":0,"Class":2,"TagBased":false,"DateEarned":"\/Date(1446023728647)\/","Name":"Good Question"},{"Id":0,"Class":2,"TagBased":false,"DateEarned":"\/Date(1446035189240)\/","Name":"Notable Question"},{"Id":0,"Class":3,"TagBased":false,"DateEarned":"\/Date(1446982729873)\/","Name":"Nice Question"}],"Id":null,"MostEarnedBadge":null},"CommentStats":{"Comments":18,"LongestCommentWordCount":70,"ShortestCommentWordCount":4,"AverageCommentWordCount":31.0555555555556,"AverageCommentScore":0.833333333333333,"TotalCommentWordCount":559,"HighestScoredComment":13,"LowestScoredComment":0,"CommentScores":[0,0,0,0,0,0,0,0,0,0,13,0,0,0,1,1,0,0],"Id":null},"Name":null,"Id":"academia.stackexchange.com-7328","AboutMe":null,"Location":null}
