{"CreationDate":"\/Date(-62135596800000)\/","AverageQuestionsPerDay":0,"AverageAnswersPerDay":0,"AveragePostsPerDay":0,"Views":0,"UpVotes":0,"DownVotes":0,"AccountId":1109,"LastAccessDate":"\/Date(-62135596800000)\/","Reputation":0,"PostStats":{"PostsMade":0,"TotalViews":0,"Questions":5,"TotalWordsForQuestions":472,"TotalWordsForAnswers":0,"TotalTitleWordCount":49,"HighestScoredQuestion":17,"LowestScoredQuestion":0,"TotalCommentsOnQuestions":0,"Answers":0,"HighestScoredAnswer":0,"LowestScoredAnswer":0,"TotalCommentsOnPosts":0,"TotalCommentsOnAnswers":0,"TotalAcceptedAnswers":0,"AverageWordsPerAnswer":0,"AverageViewsPerPost":0,"AverageAcceptedAnswers":0,"LongestQuestionWordCount":122,"ShortestQuestionWordCount":58,"LongestAnswerWordCount":0,"ShortestAnswerWordCount":0,"LongestQuestionTitleWordCount":19,"AverageQuestionTitleWordCount":0,"AverageWordsPerQuestion":94.4,"QuestionIds":[2900,2928,9633,9639,61183],"AnswerIds":[],"Id":null},"BadgeStats":{"TotalBadges":0,"TotalTagBadges":0,"Badges":[{"Id":0,"Class":3,"TagBased":false,"DateEarned":"\/Date(1289858458030)\/","Name":"Autobiographer"},{"Id":0,"Class":3,"TagBased":false,"DateEarned":"\/Date(1289862958233)\/","Name":"Student"},{"Id":0,"Class":3,"TagBased":false,"DateEarned":"\/Date(1290011160253)\/","Name":"Editor"},{"Id":0,"Class":3,"TagBased":false,"DateEarned":"\/Date(1306148351270)\/","Name":"Supporter"},{"Id":0,"Class":3,"TagBased":false,"DateEarned":"\/Date(1316954315087)\/","Name":"Popular Question"},{"Id":0,"Class":2,"TagBased":false,"DateEarned":"\/Date(1321395466530)\/","Name":"Yearling"},{"Id":0,"Class":3,"TagBased":false,"DateEarned":"\/Date(1330787818430)\/","Name":"Nice Question"},{"Id":0,"Class":2,"TagBased":false,"DateEarned":"\/Date(1331899903180)\/","Name":"Notable Question"},{"Id":0,"Class":3,"TagBased":false,"DateEarned":"\/Date(1352569862527)\/","Name":"Popular Question"},{"Id":0,"Class":2,"TagBased":false,"DateEarned":"\/Date(1375021480603)\/","Name":"Notable Question"},{"Id":0,"Class":3,"TagBased":false,"DateEarned":"\/Date(1424662805020)\/","Name":"Nice Question"},{"Id":0,"Class":1,"TagBased":false,"DateEarned":"\/Date(1432639261730)\/","Name":"Famous Question"},{"Id":0,"Class":1,"TagBased":false,"DateEarned":"\/Date(1446457656270)\/","Name":"Famous Question"}],"Id":null,"MostEarnedBadge":null},"CommentStats":{"Comments":3,"LongestCommentWordCount":35,"ShortestCommentWordCount":10,"AverageCommentWordCount":25,"AverageCommentScore":0,"TotalCommentWordCount":75,"HighestScoredComment":0,"LowestScoredComment":0,"CommentScores":[0,0,0],"Id":null},"Name":null,"Id":"android.stackexchange.com-1109","AboutMe":null,"Location":null}
