{"CreationDate":"\/Date(-62135596800000)\/","AverageQuestionsPerDay":0,"AverageAnswersPerDay":0,"AveragePostsPerDay":0,"Views":0,"UpVotes":0,"DownVotes":0,"AccountId":116661,"LastAccessDate":"\/Date(-62135596800000)\/","Reputation":0,"PostStats":{"PostsMade":0,"TotalViews":0,"Questions":1,"TotalWordsForQuestions":224,"TotalWordsForAnswers":2050,"TotalTitleWordCount":6,"HighestScoredQuestion":1,"LowestScoredQuestion":0,"TotalCommentsOnQuestions":0,"Answers":25,"HighestScoredAnswer":2,"LowestScoredAnswer":-1,"TotalCommentsOnPosts":0,"TotalCommentsOnAnswers":0,"TotalAcceptedAnswers":0,"AverageWordsPerAnswer":82,"AverageViewsPerPost":0,"AverageAcceptedAnswers":0,"LongestQuestionWordCount":224,"ShortestQuestionWordCount":224,"LongestAnswerWordCount":322,"ShortestAnswerWordCount":8,"LongestQuestionTitleWordCount":6,"AverageQuestionTitleWordCount":0,"AverageWordsPerQuestion":224,"QuestionIds":[122619],"AnswerIds":[115813,115816,116151,116159,116191,116411,116426,116429,116446,116448,116455,116532,116681,117474,119036,119037,119040,119042,120551,120554,120797,120816,120818,122414,122430],"Id":null},"BadgeStats":{"TotalBadges":0,"TotalTagBadges":0,"Badges":[{"Id":0,"Class":3,"TagBased":false,"DateEarned":"\/Date(1437406120267)\/","Name":"Teacher"},{"Id":0,"Class":3,"TagBased":false,"DateEarned":"\/Date(1437464179807)\/","Name":"Editor"},{"Id":0,"Class":3,"TagBased":false,"DateEarned":"\/Date(1439379108400)\/","Name":"Commentator"},{"Id":0,"Class":3,"TagBased":false,"DateEarned":"\/Date(1441026490237)\/","Name":"Critic"},{"Id":0,"Class":3,"TagBased":false,"DateEarned":"\/Date(1441175730683)\/","Name":"Supporter"},{"Id":0,"Class":3,"TagBased":false,"DateEarned":"\/Date(1441798236753)\/","Name":"Student"}],"Id":null,"MostEarnedBadge":null},"CommentStats":{"Comments":33,"LongestCommentWordCount":101,"ShortestCommentWordCount":4,"AverageCommentWordCount":24.8787878787879,"AverageCommentScore":0.151515151515152,"TotalCommentWordCount":821,"HighestScoredComment":2,"LowestScoredComment":0,"CommentScores":[0,0,0,1,0,0,0,0,0,0,1,0,0,0,0,0,1,2,0,0,0,0,0,0,0,0,0,0,0,0,0,0,0],"Id":null},"Name":null,"Id":"android.stackexchange.com-116661","AboutMe":null,"Location":null}
