{"CreationDate":"\/Date(-62135596800000)\/","AverageQuestionsPerDay":0,"AverageAnswersPerDay":0,"AveragePostsPerDay":0,"Views":0,"UpVotes":0,"DownVotes":0,"AccountId":124725,"LastAccessDate":"\/Date(-62135596800000)\/","Reputation":0,"PostStats":{"PostsMade":0,"TotalViews":0,"Questions":2,"TotalWordsForQuestions":182,"TotalWordsForAnswers":66,"TotalTitleWordCount":6,"HighestScoredQuestion":1,"LowestScoredQuestion":0,"TotalCommentsOnQuestions":0,"Answers":2,"HighestScoredAnswer":0,"LowestScoredAnswer":-1,"TotalCommentsOnPosts":0,"TotalCommentsOnAnswers":0,"TotalAcceptedAnswers":0,"AverageWordsPerAnswer":33,"AverageViewsPerPost":0,"AverageAcceptedAnswers":0,"LongestQuestionWordCount":100,"ShortestQuestionWordCount":82,"LongestAnswerWordCount":45,"ShortestAnswerWordCount":21,"LongestQuestionTitleWordCount":3,"AverageQuestionTitleWordCount":0,"AverageWordsPerQuestion":91,"QuestionIds":[121003,121130],"AnswerIds":[121104,122153],"Id":null},"BadgeStats":{"TotalBadges":0,"TotalTagBadges":0,"Badges":[{"Id":0,"Class":3,"TagBased":false,"DateEarned":"\/Date(1441175730683)\/","Name":"Autobiographer"},{"Id":0,"Class":3,"TagBased":false,"DateEarned":"\/Date(1441483727740)\/","Name":"Scholar"},{"Id":0,"Class":3,"TagBased":false,"DateEarned":"\/Date(1442459899623)\/","Name":"Student"}],"Id":null,"MostEarnedBadge":null},"CommentStats":{"Comments":3,"LongestCommentWordCount":9,"ShortestCommentWordCount":7,"AverageCommentWordCount":8,"AverageCommentScore":0,"TotalCommentWordCount":24,"HighestScoredComment":0,"LowestScoredComment":0,"CommentScores":[0,0,0],"Id":null},"Name":null,"Id":"android.stackexchange.com-124725","AboutMe":null,"Location":null}
