{"CreationDate":"\/Date(-62135596800000)\/","AverageQuestionsPerDay":0,"AverageAnswersPerDay":0,"AveragePostsPerDay":0,"Views":0,"UpVotes":0,"DownVotes":0,"AccountId":15300,"LastAccessDate":"\/Date(-62135596800000)\/","Reputation":0,"PostStats":{"PostsMade":0,"TotalViews":0,"Questions":1,"TotalWordsForQuestions":88,"TotalWordsForAnswers":0,"TotalTitleWordCount":14,"HighestScoredQuestion":30,"LowestScoredQuestion":0,"TotalCommentsOnQuestions":0,"Answers":0,"HighestScoredAnswer":0,"LowestScoredAnswer":0,"TotalCommentsOnPosts":0,"TotalCommentsOnAnswers":0,"TotalAcceptedAnswers":0,"AverageWordsPerAnswer":0,"AverageViewsPerPost":0,"AverageAcceptedAnswers":0,"LongestQuestionWordCount":88,"ShortestQuestionWordCount":88,"LongestAnswerWordCount":0,"ShortestAnswerWordCount":0,"LongestQuestionTitleWordCount":14,"AverageQuestionTitleWordCount":0,"AverageWordsPerQuestion":88,"QuestionIds":[23357],"AnswerIds":[],"Id":null},"BadgeStats":{"TotalBadges":0,"TotalTagBadges":0,"Badges":[{"Id":0,"Class":3,"TagBased":false,"DateEarned":"\/Date(1337736501610)\/","Name":"Autobiographer"},{"Id":0,"Class":3,"TagBased":false,"DateEarned":"\/Date(1337736802383)\/","Name":"Student"},{"Id":0,"Class":3,"TagBased":false,"DateEarned":"\/Date(1337796803880)\/","Name":"Scholar"},{"Id":0,"Class":3,"TagBased":false,"DateEarned":"\/Date(1338500513837)\/","Name":"Supporter"},{"Id":0,"Class":3,"TagBased":false,"DateEarned":"\/Date(1341342613697)\/","Name":"Nice Question"},{"Id":0,"Class":3,"TagBased":false,"DateEarned":"\/Date(1344619543803)\/","Name":"Popular Question"},{"Id":0,"Class":2,"TagBased":false,"DateEarned":"\/Date(1350140074910)\/","Name":"Notable Question"},{"Id":0,"Class":1,"TagBased":false,"DateEarned":"\/Date(1376743453160)\/","Name":"Famous Question"},{"Id":0,"Class":2,"TagBased":false,"DateEarned":"\/Date(1428951935990)\/","Name":"Good Question"}],"Id":null,"MostEarnedBadge":null},"CommentStats":{"Comments":8,"LongestCommentWordCount":88,"ShortestCommentWordCount":10,"AverageCommentWordCount":43,"AverageCommentScore":0,"TotalCommentWordCount":344,"HighestScoredComment":0,"LowestScoredComment":0,"CommentScores":[0,0,0,0,0,0,0,0],"Id":null},"Name":null,"Id":"android.stackexchange.com-15300","AboutMe":null,"Location":null}
