{"CreationDate":"\/Date(-62135596800000)\/","AverageQuestionsPerDay":0,"AverageAnswersPerDay":0,"AveragePostsPerDay":0,"Views":0,"UpVotes":0,"DownVotes":0,"AccountId":16112,"LastAccessDate":"\/Date(-62135596800000)\/","Reputation":0,"PostStats":{"PostsMade":0,"TotalViews":0,"Questions":54,"TotalWordsForQuestions":3801,"TotalWordsForAnswers":303,"TotalTitleWordCount":438,"HighestScoredQuestion":23,"LowestScoredQuestion":-1,"TotalCommentsOnQuestions":0,"Answers":5,"HighestScoredAnswer":4,"LowestScoredAnswer":0,"TotalCommentsOnPosts":0,"TotalCommentsOnAnswers":0,"TotalAcceptedAnswers":0,"AverageWordsPerAnswer":60.6,"AverageViewsPerPost":0,"AverageAcceptedAnswers":0,"LongestQuestionWordCount":196,"ShortestQuestionWordCount":14,"LongestAnswerWordCount":118,"ShortestAnswerWordCount":10,"LongestQuestionTitleWordCount":19,"AverageQuestionTitleWordCount":0,"AverageWordsPerQuestion":70.3888888888889,"QuestionIds":[25430,25447,25567,25706,25816,25980,26632,26635,26826,26964,27257,27259,27260,27516,27644,27816,28017,28129,30037,30216,30320,30396,31830,32162,32306,32363,32365,32405,32406,32541,32649,32650,32766,32768,32769,32770,32772,33063,33064,33067,36708,36899,37040,37383,37795,40517,41353,44183,45333,45952,56093,56102,105985,106136],"AnswerIds":[25817,26633,26825,27258,36900],"Id":null},"BadgeStats":{"TotalBadges":0,"TotalTagBadges":0,"Badges":[{"Id":0,"Class":3,"TagBased":false,"DateEarned":"\/Date(1340100035797)\/","Name":"Autobiographer"},{"Id":0,"Class":3,"TagBased":false,"DateEarned":"\/Date(1340101837577)\/","Name":"Student"},{"Id":0,"Class":3,"TagBased":false,"DateEarned":"\/Date(1341685444120)\/","Name":"Supporter"},{"Id":0,"Class":3,"TagBased":false,"DateEarned":"\/Date(1341737946473)\/","Name":"Editor"},{"Id":0,"Class":3,"TagBased":false,"DateEarned":"\/Date(1342087133667)\/","Name":"Scholar"},{"Id":0,"Class":3,"TagBased":false,"DateEarned":"\/Date(1342264004783)\/","Name":"Teacher"},{"Id":0,"Class":3,"TagBased":false,"DateEarned":"\/Date(1344095083797)\/","Name":"Commentator"},{"Id":0,"Class":3,"TagBased":false,"DateEarned":"\/Date(1345074719270)\/","Name":"Tumbleweed"},{"Id":0,"Class":3,"TagBased":false,"DateEarned":"\/Date(1345991938763)\/","Name":"Critic"},{"Id":0,"Class":3,"TagBased":false,"DateEarned":"\/Date(1349607640570)\/","Name":"Nice Question"},{"Id":0,"Class":3,"TagBased":false,"DateEarned":"\/Date(1349963004633)\/","Name":"Popular Question"},{"Id":0,"Class":3,"TagBased":false,"DateEarned":"\/Date(1350589957087)\/","Name":"Nice Question"},{"Id":0,"Class":3,"TagBased":false,"DateEarned":"\/Date(1351125448377)\/","Name":"Nice Question"},{"Id":0,"Class":3,"TagBased":false,"DateEarned":"\/Date(1351245458887)\/","Name":"Excavator"},{"Id":0,"Class":3,"TagBased":false,"DateEarned":"\/Date(1351625010050)\/","Name":"Citizen Patrol"},{"Id":0,"Class":3,"TagBased":false,"DateEarned":"\/Date(1351626210857)\/","Name":"Suffrage"},{"Id":0,"Class":3,"TagBased":false,"DateEarned":"\/Date(1351800889280)\/","Name":"Custodian"},{"Id":0,"Class":3,"TagBased":false,"DateEarned":"\/Date(1353311611813)\/","Name":"Popular Question"},{"Id":0,"Class":3,"TagBased":false,"DateEarned":"\/Date(1353988578467)\/","Name":"Caucus"},{"Id":0,"Class":3,"TagBased":false,"DateEarned":"\/Date(1353991579260)\/","Name":"Vox Populi"},{"Id":0,"Class":3,"TagBased":false,"DateEarned":"\/Date(1354128533853)\/","Name":"Popular Question"},{"Id":0,"Class":3,"TagBased":false,"DateEarned":"\/Date(1354164835507)\/","Name":"Custodian"},{"Id":0,"Class":2,"TagBased":false,"DateEarned":"\/Date(1354611291570)\/","Name":"Constituent"},{"Id":0,"Class":2,"TagBased":false,"DateEarned":"\/Date(1354701899560)\/","Name":"Notable Question"},{"Id":0,"Class":3,"TagBased":false,"DateEarned":"\/Date(1356083018283)\/","Name":"Popular Question"},{"Id":0,"Class":2,"TagBased":false,"DateEarned":"\/Date(1357453061580)\/","Name":"Notable Question"},{"Id":0,"Class":3,"TagBased":false,"DateEarned":"\/Date(1359081250780)\/","Name":"Popular Question"},{"Id":0,"Class":3,"TagBased":false,"DateEarned":"\/Date(1359237371250)\/","Name":"Popular Question"},{"Id":0,"Class":2,"TagBased":false,"DateEarned":"\/Date(1359604951323)\/","Name":"Notable Question"},{"Id":0,"Class":3,"TagBased":false,"DateEarned":"\/Date(1361816715227)\/","Name":"Popular Question"},{"Id":0,"Class":3,"TagBased":false,"DateEarned":"\/Date(1361821515157)\/","Name":"Popular Question"},{"Id":0,"Class":3,"TagBased":false,"DateEarned":"\/Date(1363033238850)\/","Name":"Popular Question"},{"Id":0,"Class":3,"TagBased":false,"DateEarned":"\/Date(1364119808800)\/","Name":"Popular Question"},{"Id":0,"Class":3,"TagBased":false,"DateEarned":"\/Date(1364177316473)\/","Name":"Popular Question"},{"Id":0,"Class":3,"TagBased":false,"DateEarned":"\/Date(1364707270527)\/","Name":"Popular Question"},{"Id":0,"Class":2,"TagBased":false,"DateEarned":"\/Date(1365608278600)\/","Name":"Notable Question"},{"Id":0,"Class":2,"TagBased":false,"DateEarned":"\/Date(1369256768240)\/","Name":"Notable Question"},{"Id":0,"Class":2,"TagBased":false,"DateEarned":"\/Date(1369271787083)\/","Name":"Notable Question"},{"Id":0,"Class":3,"TagBased":false,"DateEarned":"\/Date(1370734512200)\/","Name":"Popular Question"},{"Id":0,"Class":1,"TagBased":false,"DateEarned":"\/Date(1370882289283)\/","Name":"Famous Question"},{"Id":0,"Class":2,"TagBased":false,"DateEarned":"\/Date(1370968209687)\/","Name":"Notable Question"},{"Id":0,"Class":2,"TagBased":false,"DateEarned":"\/Date(1371636571933)\/","Name":"Yearling"},{"Id":0,"Class":3,"TagBased":false,"DateEarned":"\/Date(1372779807347)\/","Name":"Popular Question"},{"Id":0,"Class":3,"TagBased":false,"DateEarned":"\/Date(1373109371847)\/","Name":"Popular Question"},{"Id":0,"Class":3,"TagBased":false,"DateEarned":"\/Date(1373881863173)\/","Name":"Popular Question"},{"Id":0,"Class":2,"TagBased":false,"DateEarned":"\/Date(1376068036893)\/","Name":"Notable Question"},{"Id":0,"Class":1,"TagBased":false,"DateEarned":"\/Date(1377089981313)\/","Name":"Famous Question"},{"Id":0,"Class":3,"TagBased":false,"DateEarned":"\/Date(1378307006490)\/","Name":"Popular Question"},{"Id":0,"Class":2,"TagBased":false,"DateEarned":"\/Date(1379327955053)\/","Name":"Notable Question"},{"Id":0,"Class":3,"TagBased":false,"DateEarned":"\/Date(1380273822063)\/","Name":"Popular Question"},{"Id":0,"Class":2,"TagBased":false,"DateEarned":"\/Date(1380306666837)\/","Name":"Notable Question"},{"Id":0,"Class":2,"TagBased":false,"DateEarned":"\/Date(1380320206697)\/","Name":"Notable Question"},{"Id":0,"Class":2,"TagBased":false,"DateEarned":"\/Date(1380468691513)\/","Name":"Notable Question"},{"Id":0,"Class":3,"TagBased":false,"DateEarned":"\/Date(1381421622537)\/","Name":"Popular Question"},{"Id":0,"Class":3,"TagBased":false,"DateEarned":"\/Date(1383239661637)\/","Name":"Peer Pressure"},{"Id":0,"Class":3,"TagBased":false,"DateEarned":"\/Date(1384158497320)\/","Name":"Popular Question"},{"Id":0,"Class":2,"TagBased":false,"DateEarned":"\/Date(1385836016763)\/","Name":"Civic Duty"},{"Id":0,"Class":2,"TagBased":false,"DateEarned":"\/Date(1386325300120)\/","Name":"Notable Question"},{"Id":0,"Class":3,"TagBased":false,"DateEarned":"\/Date(1389107712730)\/","Name":"Popular Question"},{"Id":0,"Class":3,"TagBased":false,"DateEarned":"\/Date(1389532779183)\/","Name":"Self-Learner"},{"Id":0,"Class":3,"TagBased":false,"DateEarned":"\/Date(1393473873983)\/","Name":"Popular Question"},{"Id":0,"Class":2,"TagBased":false,"DateEarned":"\/Date(1397617148477)\/","Name":"Notable Question"},{"Id":0,"Class":2,"TagBased":false,"DateEarned":"\/Date(1398312655027)\/","Name":"Notable Question"},{"Id":0,"Class":3,"TagBased":false,"DateEarned":"\/Date(1399223688930)\/","Name":"Nice Question"},{"Id":0,"Class":2,"TagBased":false,"DateEarned":"\/Date(1403171907477)\/","Name":"Yearling"},{"Id":0,"Class":1,"TagBased":false,"DateEarned":"\/Date(1404196341780)\/","Name":"Famous Question"},{"Id":0,"Class":3,"TagBased":false,"DateEarned":"\/Date(1408641574983)\/","Name":"Popular Question"},{"Id":0,"Class":1,"TagBased":false,"DateEarned":"\/Date(1410244856050)\/","Name":"Famous Question"},{"Id":0,"Class":3,"TagBased":false,"DateEarned":"\/Date(1413798820630)\/","Name":"Popular Question"},{"Id":0,"Class":1,"TagBased":false,"DateEarned":"\/Date(1419075010143)\/","Name":"Famous Question"},{"Id":0,"Class":3,"TagBased":false,"DateEarned":"\/Date(1424326278973)\/","Name":"Popular Question"},{"Id":0,"Class":3,"TagBased":false,"DateEarned":"\/Date(1424849055670)\/","Name":"Popular Question"},{"Id":0,"Class":1,"TagBased":false,"DateEarned":"\/Date(1424930703603)\/","Name":"Famous Question"},{"Id":0,"Class":2,"TagBased":false,"DateEarned":"\/Date(1425885262657)\/","Name":"Notable Question"},{"Id":0,"Class":2,"TagBased":false,"DateEarned":"\/Date(1432418040337)\/","Name":"Notable Question"},{"Id":0,"Class":2,"TagBased":false,"DateEarned":"\/Date(1434708044033)\/","Name":"Yearling"},{"Id":0,"Class":3,"TagBased":false,"DateEarned":"\/Date(1436689679860)\/","Name":"Nice Question"},{"Id":0,"Class":3,"TagBased":false,"DateEarned":"\/Date(1439910549337)\/","Name":"Popular Question"},{"Id":0,"Class":2,"TagBased":false,"DateEarned":"\/Date(1441928877843)\/","Name":"Notable Question"},{"Id":0,"Class":2,"TagBased":false,"DateEarned":"\/Date(1442727010967)\/","Name":"Notable Question"},{"Id":0,"Class":2,"TagBased":false,"DateEarned":"\/Date(1446565425280)\/","Name":"Notable Question"},{"Id":0,"Class":3,"TagBased":false,"DateEarned":"\/Date(1446659797093)\/","Name":"Popular Question"},{"Id":0,"Class":2,"TagBased":false,"DateEarned":"\/Date(1449741653760)\/","Name":"Notable Question"}],"Id":null,"MostEarnedBadge":null},"CommentStats":{"Comments":22,"LongestCommentWordCount":47,"ShortestCommentWordCount":2,"AverageCommentWordCount":14,"AverageCommentScore":0.181818181818182,"TotalCommentWordCount":308,"HighestScoredComment":1,"LowestScoredComment":0,"CommentScores":[0,0,0,0,0,0,0,0,0,0,0,1,0,0,1,0,0,0,1,0,1,0],"Id":null},"Name":null,"Id":"android.stackexchange.com-16112","AboutMe":null,"Location":null}
