{"CreationDate":"\/Date(-62135596800000)\/","AverageQuestionsPerDay":0,"AverageAnswersPerDay":0,"AveragePostsPerDay":0,"Views":0,"UpVotes":0,"DownVotes":0,"AccountId":18593,"LastAccessDate":"\/Date(-62135596800000)\/","Reputation":0,"PostStats":{"PostsMade":0,"TotalViews":0,"Questions":2,"TotalWordsForQuestions":101,"TotalWordsForAnswers":0,"TotalTitleWordCount":20,"HighestScoredQuestion":1,"LowestScoredQuestion":0,"TotalCommentsOnQuestions":0,"Answers":0,"HighestScoredAnswer":0,"LowestScoredAnswer":0,"TotalCommentsOnPosts":0,"TotalCommentsOnAnswers":0,"TotalAcceptedAnswers":0,"AverageWordsPerAnswer":0,"AverageViewsPerPost":0,"AverageAcceptedAnswers":0,"LongestQuestionWordCount":56,"ShortestQuestionWordCount":45,"LongestAnswerWordCount":0,"ShortestAnswerWordCount":0,"LongestQuestionTitleWordCount":15,"AverageQuestionTitleWordCount":0,"AverageWordsPerQuestion":50.5,"QuestionIds":[49807,59730],"AnswerIds":[],"Id":null},"BadgeStats":{"TotalBadges":0,"TotalTagBadges":0,"Badges":[{"Id":0,"Class":3,"TagBased":false,"DateEarned":"\/Date(1374653824563)\/","Name":"Student"},{"Id":0,"Class":3,"TagBased":false,"DateEarned":"\/Date(1374719258527)\/","Name":"Custodian"},{"Id":0,"Class":3,"TagBased":false,"DateEarned":"\/Date(1374719869630)\/","Name":"Supporter"},{"Id":0,"Class":3,"TagBased":false,"DateEarned":"\/Date(1377659080983)\/","Name":"Autobiographer"},{"Id":0,"Class":3,"TagBased":false,"DateEarned":"\/Date(1388396771173)\/","Name":"Scholar"}],"Id":null,"MostEarnedBadge":null},"CommentStats":{"Comments":5,"LongestCommentWordCount":90,"ShortestCommentWordCount":17,"AverageCommentWordCount":42.4,"AverageCommentScore":0,"TotalCommentWordCount":212,"HighestScoredComment":0,"LowestScoredComment":0,"CommentScores":[0,0,0,0,0],"Id":null},"Name":null,"Id":"android.stackexchange.com-18593","AboutMe":null,"Location":null}
