{"CreationDate":"\/Date(-62135596800000)\/","AverageQuestionsPerDay":0,"AverageAnswersPerDay":0,"AveragePostsPerDay":0,"Views":0,"UpVotes":0,"DownVotes":0,"AccountId":19059,"LastAccessDate":"\/Date(-62135596800000)\/","Reputation":0,"PostStats":{"PostsMade":0,"TotalViews":0,"Questions":0,"TotalWordsForQuestions":0,"TotalWordsForAnswers":28,"TotalTitleWordCount":0,"HighestScoredQuestion":0,"LowestScoredQuestion":0,"TotalCommentsOnQuestions":0,"Answers":1,"HighestScoredAnswer":6,"LowestScoredAnswer":0,"TotalCommentsOnPosts":0,"TotalCommentsOnAnswers":0,"TotalAcceptedAnswers":0,"AverageWordsPerAnswer":28,"AverageViewsPerPost":0,"AverageAcceptedAnswers":0,"LongestQuestionWordCount":0,"ShortestQuestionWordCount":0,"LongestAnswerWordCount":28,"ShortestAnswerWordCount":28,"LongestQuestionTitleWordCount":0,"AverageQuestionTitleWordCount":0,"AverageWordsPerQuestion":0,"QuestionIds":[],"AnswerIds":[52919],"Id":null},"BadgeStats":{"TotalBadges":0,"TotalTagBadges":0,"Badges":[{"Id":0,"Class":3,"TagBased":false,"DateEarned":"\/Date(1347278477677)\/","Name":"Supporter"},{"Id":0,"Class":3,"TagBased":false,"DateEarned":"\/Date(1378819619737)\/","Name":"Revival"},{"Id":0,"Class":3,"TagBased":false,"DateEarned":"\/Date(1378819619737)\/","Name":"Teacher"},{"Id":0,"Class":3,"TagBased":false,"DateEarned":"\/Date(1400978805453)\/","Name":"Informed"},{"Id":0,"Class":3,"TagBased":false,"DateEarned":"\/Date(1421926718880)\/","Name":"Autobiographer"},{"Id":0,"Class":2,"TagBased":false,"DateEarned":"\/Date(1437498535917)\/","Name":"Necromancer"}],"Id":null,"MostEarnedBadge":null},"CommentStats":{"Comments":1,"LongestCommentWordCount":31,"ShortestCommentWordCount":31,"AverageCommentWordCount":31,"AverageCommentScore":0,"TotalCommentWordCount":31,"HighestScoredComment":0,"LowestScoredComment":0,"CommentScores":[0],"Id":null},"Name":null,"Id":"android.stackexchange.com-19059","AboutMe":null,"Location":null}
