{"CreationDate":"\/Date(-62135596800000)\/","AverageQuestionsPerDay":0,"AverageAnswersPerDay":0,"AveragePostsPerDay":0,"Views":0,"UpVotes":0,"DownVotes":0,"AccountId":23156,"LastAccessDate":"\/Date(-62135596800000)\/","Reputation":0,"PostStats":{"PostsMade":0,"TotalViews":0,"Questions":2,"TotalWordsForQuestions":126,"TotalWordsForAnswers":809,"TotalTitleWordCount":12,"HighestScoredQuestion":5,"LowestScoredQuestion":0,"TotalCommentsOnQuestions":0,"Answers":11,"HighestScoredAnswer":5,"LowestScoredAnswer":0,"TotalCommentsOnPosts":0,"TotalCommentsOnAnswers":0,"TotalAcceptedAnswers":0,"AverageWordsPerAnswer":73.5454545454545,"AverageViewsPerPost":0,"AverageAcceptedAnswers":0,"LongestQuestionWordCount":81,"ShortestQuestionWordCount":45,"LongestAnswerWordCount":228,"ShortestAnswerWordCount":28,"LongestQuestionTitleWordCount":6,"AverageQuestionTitleWordCount":0,"AverageWordsPerQuestion":63,"QuestionIds":[32809,33847],"AnswerIds":[32932,33052,33072,33123,33126,33127,33673,33679,33853,33904,50698],"Id":null},"BadgeStats":{"TotalBadges":0,"TotalTagBadges":0,"Badges":[{"Id":0,"Class":3,"TagBased":false,"DateEarned":"\/Date(1351858797450)\/","Name":"Autobiographer"},{"Id":0,"Class":3,"TagBased":false,"DateEarned":"\/Date(1351876198240)\/","Name":"Student"},{"Id":0,"Class":3,"TagBased":false,"DateEarned":"\/Date(1352110325393)\/","Name":"Supporter"},{"Id":0,"Class":3,"TagBased":false,"DateEarned":"\/Date(1352115135153)\/","Name":"Teacher"},{"Id":0,"Class":3,"TagBased":false,"DateEarned":"\/Date(1352290425700)\/","Name":"Citizen Patrol"},{"Id":0,"Class":3,"TagBased":false,"DateEarned":"\/Date(1352400893960)\/","Name":"Commentator"},{"Id":0,"Class":3,"TagBased":false,"DateEarned":"\/Date(1352457596403)\/","Name":"Critic"},{"Id":0,"Class":3,"TagBased":false,"DateEarned":"\/Date(1353344012150)\/","Name":"Editor"},{"Id":0,"Class":3,"TagBased":false,"DateEarned":"\/Date(1353344012150)\/","Name":"Scholar"},{"Id":0,"Class":3,"TagBased":false,"DateEarned":"\/Date(1353344311967)\/","Name":"Analytical"},{"Id":0,"Class":3,"TagBased":false,"DateEarned":"\/Date(1353496430073)\/","Name":"Custodian"},{"Id":0,"Class":3,"TagBased":false,"DateEarned":"\/Date(1353496430073)\/","Name":"Custodian"},{"Id":0,"Class":3,"TagBased":false,"DateEarned":"\/Date(1354035380467)\/","Name":"Caucus"},{"Id":0,"Class":3,"TagBased":false,"DateEarned":"\/Date(1367725180737)\/","Name":"Popular Question"},{"Id":0,"Class":2,"TagBased":false,"DateEarned":"\/Date(1375086297407)\/","Name":"Notable Question"},{"Id":0,"Class":2,"TagBased":false,"DateEarned":"\/Date(1383394905963)\/","Name":"Yearling"},{"Id":0,"Class":3,"TagBased":false,"DateEarned":"\/Date(1412119028073)\/","Name":"Explainer"},{"Id":0,"Class":2,"TagBased":false,"DateEarned":"\/Date(1414930984370)\/","Name":"Yearling"}],"Id":null,"MostEarnedBadge":null},"CommentStats":{"Comments":25,"LongestCommentWordCount":46,"ShortestCommentWordCount":4,"AverageCommentWordCount":20.08,"AverageCommentScore":0.44,"TotalCommentWordCount":502,"HighestScoredComment":3,"LowestScoredComment":0,"CommentScores":[0,0,3,0,0,0,1,0,1,0,0,0,1,0,0,3,0,0,0,1,0,0,1,0,0],"Id":null},"Name":null,"Id":"android.stackexchange.com-23156","AboutMe":null,"Location":null}
