{"CreationDate":"\/Date(-62135596800000)\/","AverageQuestionsPerDay":0,"AverageAnswersPerDay":0,"AveragePostsPerDay":0,"Views":0,"UpVotes":0,"DownVotes":0,"AccountId":5934,"LastAccessDate":"\/Date(-62135596800000)\/","Reputation":0,"PostStats":{"PostsMade":0,"TotalViews":0,"Questions":6,"TotalWordsForQuestions":993,"TotalWordsForAnswers":231,"TotalTitleWordCount":55,"HighestScoredQuestion":13,"LowestScoredQuestion":0,"TotalCommentsOnQuestions":0,"Answers":3,"HighestScoredAnswer":1,"LowestScoredAnswer":0,"TotalCommentsOnPosts":0,"TotalCommentsOnAnswers":0,"TotalAcceptedAnswers":0,"AverageWordsPerAnswer":77,"AverageViewsPerPost":0,"AverageAcceptedAnswers":0,"LongestQuestionWordCount":210,"ShortestQuestionWordCount":67,"LongestAnswerWordCount":111,"ShortestAnswerWordCount":54,"LongestQuestionTitleWordCount":13,"AverageQuestionTitleWordCount":0,"AverageWordsPerQuestion":165.5,"QuestionIds":[35084,51091,60549,60746,127300,136435],"AnswerIds":[60654,67396,136441],"Id":null},"BadgeStats":{"TotalBadges":0,"TotalTagBadges":0,"Badges":[{"Id":0,"Class":3,"TagBased":false,"DateEarned":"\/Date(1308171563787)\/","Name":"Supporter"},{"Id":0,"Class":3,"TagBased":false,"DateEarned":"\/Date(1350558156683)\/","Name":"Autobiographer"},{"Id":0,"Class":3,"TagBased":false,"DateEarned":"\/Date(1355135886147)\/","Name":"Student"},{"Id":0,"Class":3,"TagBased":false,"DateEarned":"\/Date(1355156886303)\/","Name":"Editor"},{"Id":0,"Class":3,"TagBased":false,"DateEarned":"\/Date(1367750191807)\/","Name":"Tumbleweed"},{"Id":0,"Class":3,"TagBased":false,"DateEarned":"\/Date(1369351678413)\/","Name":"Popular Question"},{"Id":0,"Class":3,"TagBased":false,"DateEarned":"\/Date(1370616631550)\/","Name":"Critic"},{"Id":0,"Class":3,"TagBased":false,"DateEarned":"\/Date(1375872619493)\/","Name":"Promoter"},{"Id":0,"Class":3,"TagBased":false,"DateEarned":"\/Date(1376558935317)\/","Name":"Commentator"},{"Id":0,"Class":3,"TagBased":false,"DateEarned":"\/Date(1376559840307)\/","Name":"Benefactor"},{"Id":0,"Class":3,"TagBased":false,"DateEarned":"\/Date(1376580923007)\/","Name":"Scholar"},{"Id":0,"Class":2,"TagBased":false,"DateEarned":"\/Date(1383756140667)\/","Name":"Notable Question"},{"Id":0,"Class":3,"TagBased":false,"DateEarned":"\/Date(1389174092657)\/","Name":"Teacher"},{"Id":0,"Class":3,"TagBased":false,"DateEarned":"\/Date(1397412250637)\/","Name":"Popular Question"},{"Id":0,"Class":3,"TagBased":false,"DateEarned":"\/Date(1399459475630)\/","Name":"Popular Question"},{"Id":0,"Class":3,"TagBased":false,"DateEarned":"\/Date(1401202845283)\/","Name":"Nice Question"},{"Id":0,"Class":2,"TagBased":false,"DateEarned":"\/Date(1404362028970)\/","Name":"Notable Question"},{"Id":0,"Class":1,"TagBased":false,"DateEarned":"\/Date(1417466467620)\/","Name":"Famous Question"},{"Id":0,"Class":2,"TagBased":false,"DateEarned":"\/Date(1420980850513)\/","Name":"Notable Question"},{"Id":0,"Class":3,"TagBased":false,"DateEarned":"\/Date(1430690914653)\/","Name":"Popular Question"},{"Id":0,"Class":1,"TagBased":false,"DateEarned":"\/Date(1453666754940)\/","Name":"Famous Question"}],"Id":null,"MostEarnedBadge":null},"CommentStats":{"Comments":20,"LongestCommentWordCount":51,"ShortestCommentWordCount":4,"AverageCommentWordCount":21.4,"AverageCommentScore":0.2,"TotalCommentWordCount":428,"HighestScoredComment":2,"LowestScoredComment":0,"CommentScores":[0,0,0,0,0,2,0,0,0,0,0,0,0,0,2,0,0,0,0,0],"Id":null},"Name":null,"Id":"android.stackexchange.com-5934","AboutMe":null,"Location":null}
