{"CreationDate":"\/Date(-62135596800000)\/","AverageQuestionsPerDay":0,"AverageAnswersPerDay":0,"AveragePostsPerDay":0,"Views":0,"UpVotes":0,"DownVotes":0,"AccountId":8953,"LastAccessDate":"\/Date(-62135596800000)\/","Reputation":0,"PostStats":{"PostsMade":0,"TotalViews":0,"Questions":1,"TotalWordsForQuestions":159,"TotalWordsForAnswers":0,"TotalTitleWordCount":6,"HighestScoredQuestion":5,"LowestScoredQuestion":0,"TotalCommentsOnQuestions":0,"Answers":0,"HighestScoredAnswer":0,"LowestScoredAnswer":0,"TotalCommentsOnPosts":0,"TotalCommentsOnAnswers":0,"TotalAcceptedAnswers":0,"AverageWordsPerAnswer":0,"AverageViewsPerPost":0,"AverageAcceptedAnswers":0,"LongestQuestionWordCount":159,"ShortestQuestionWordCount":159,"LongestAnswerWordCount":0,"ShortestAnswerWordCount":0,"LongestQuestionTitleWordCount":6,"AverageQuestionTitleWordCount":0,"AverageWordsPerQuestion":159,"QuestionIds":[40450],"AnswerIds":[],"Id":null},"BadgeStats":{"TotalBadges":0,"TotalTagBadges":0,"Badges":[{"Id":0,"Class":3,"TagBased":false,"DateEarned":"\/Date(1319036515350)\/","Name":"Autobiographer"},{"Id":0,"Class":3,"TagBased":false,"DateEarned":"\/Date(1332553104270)\/","Name":"Supporter"},{"Id":0,"Class":3,"TagBased":false,"DateEarned":"\/Date(1341239946583)\/","Name":"Student"},{"Id":0,"Class":3,"TagBased":false,"DateEarned":"\/Date(1361999958743)\/","Name":"Editor"},{"Id":0,"Class":3,"TagBased":false,"DateEarned":"\/Date(1362063933583)\/","Name":"Scholar"},{"Id":0,"Class":3,"TagBased":false,"DateEarned":"\/Date(1365987961383)\/","Name":"Popular Question"},{"Id":0,"Class":2,"TagBased":false,"DateEarned":"\/Date(1368724072317)\/","Name":"Notable Question"},{"Id":0,"Class":1,"TagBased":false,"DateEarned":"\/Date(1384474033487)\/","Name":"Famous Question"}],"Id":null,"MostEarnedBadge":null},"CommentStats":{"Comments":2,"LongestCommentWordCount":34,"ShortestCommentWordCount":20,"AverageCommentWordCount":27,"AverageCommentScore":0,"TotalCommentWordCount":54,"HighestScoredComment":0,"LowestScoredComment":0,"CommentScores":[0,0],"Id":null},"Name":null,"Id":"android.stackexchange.com-8953","AboutMe":null,"Location":null}
