{"CreationDate":"\/Date(1456692646507)\/","AverageQuestionsPerDay":0,"AverageAnswersPerDay":0,"AveragePostsPerDay":0,"Views":2,"UpVotes":0,"DownVotes":0,"AccountId":9148,"LastAccessDate":"\/Date(1457183401390)\/","Reputation":106,"PostStats":{"PostsMade":0,"TotalViews":0,"Questions":1,"TotalWordsForQuestions":57,"TotalWordsForAnswers":0,"TotalTitleWordCount":13,"HighestScoredQuestion":3,"LowestScoredQuestion":0,"TotalCommentsOnQuestions":0,"Answers":0,"HighestScoredAnswer":0,"LowestScoredAnswer":0,"TotalCommentsOnPosts":0,"TotalCommentsOnAnswers":0,"TotalAcceptedAnswers":0,"AverageWordsPerAnswer":0,"AverageViewsPerPost":0,"AverageAcceptedAnswers":0,"LongestQuestionWordCount":57,"ShortestQuestionWordCount":57,"LongestAnswerWordCount":0,"ShortestAnswerWordCount":0,"LongestQuestionTitleWordCount":13,"AverageQuestionTitleWordCount":0,"AverageWordsPerQuestion":57,"QuestionIds":[15034],"AnswerIds":[],"Id":null},"BadgeStats":{"TotalBadges":0,"TotalTagBadges":0,"Badges":[{"Id":0,"Class":3,"TagBased":false,"DateEarned":"\/Date(1319765293007)\/","Name":"Editor"},{"Id":0,"Class":3,"TagBased":false,"DateEarned":"\/Date(1324505510027)\/","Name":"Student"},{"Id":0,"Class":3,"TagBased":false,"DateEarned":"\/Date(1324611491367)\/","Name":"Scholar"},{"Id":0,"Class":3,"TagBased":false,"DateEarned":"\/Date(1324611491473)\/","Name":"Supporter"},{"Id":0,"Class":3,"TagBased":false,"DateEarned":"\/Date(1397141503797)\/","Name":"Popular Question"}],"Id":null,"MostEarnedBadge":null},"CommentStats":{"Comments":3,"LongestCommentWordCount":27,"ShortestCommentWordCount":7,"AverageCommentWordCount":20.3333333333333,"AverageCommentScore":0.666666666666667,"TotalCommentWordCount":61,"HighestScoredComment":2,"LowestScoredComment":0,"CommentScores":[0,0,2],"Id":null},"Name":"Confusion","Id":"android.stackexchange.com-9148","AboutMe":"<p>Software engineer working on a model based testing tool. Experienced in Ruby, Java,  Python, AWK and associated technologies. Dabbles in Clojure, Haskell, Racket and C.</p>\n","Location":""}
